setup.cfg
setup.py
pydetector/__init__.py
pydetector/__main__.py
pydetector/ast_checks.py
pydetector/astexport.py
pydetector/cli.py
pydetector/detector.py
pydetector/regexp_checks.py
pydetector/version.py
pydetector.egg-info/PKG-INFO
pydetector.egg-info/SOURCES.txt
pydetector.egg-info/dependency_links.txt
pydetector.egg-info/entry_points.txt
pydetector.egg-info/requires.txt
pydetector.egg-info/top_level.txt