Metadata-Version: 1.1
Name: pydetector
Version: 0.4.8
Summary: Python command line application & package to guess the Python version of a file
Home-page: https://github.com/juanjux/python-pydetector
Author: Juanjo Alvarez
Author-email: juanjo@juanjoalvarez.net
License: MIT
Download-URL: https://github.com/juanjux/python-pydetector/archive/0.4.8.tar.gz
Platform: UNKNOWN
Classifier: Development Status :: 4 - Beta
Classifier: Environment :: Console
Classifier: Intended Audience :: Developers
Classifier: Topic :: Software Development :: Compilers
Classifier: Topic :: Software Development :: Disassemblers
Classifier: License :: OSI Approved :: MIT License
Classifier: Operating System :: OS Independent
Classifier: Programming Language :: Python :: 3
Classifier: Programming Language :: Python :: 3.5
